best_dev_utilsssss/__init__.py
best_dev_utilsssss/dev_tools.py
best_dev_utilsssss/file_ops.py
best_dev_utilsssss/network_utils.py
best_dev_utilsssss/sys_info.py
best_dev_utilsssss/utils/__init__.py
best_dev_utilsssss/utils/helpers.py
best_dev_utilsssss-0.3.1.dist-info/METADATA
best_dev_utilsssss-0.3.1.dist-info/WHEEL
best_dev_utilsssss-0.3.1.dist-info/top_level.txt
best_dev_utilsssss-0.3.1.dist-info/RECORD
